<?xml version="1.0" encoding="UTF-8" standalone="yes"?>
<List xmlns:xsi="http://www.w3.org/2001/XMLSchema-instance">
	<Employee>
		<surname>Сидоров</surname>
		<name>Петр</name>
		<fullname>Петрович</fullname>
		<birthdate>21.03.1981</birthdate>
		<dep>Снабжение</dep>
		<pos>Кладовщик</pos>
		<type>Ставка</type>
		<pay>6500</pay>
	</Employee>
	<Employee>
		<surname>Иванов</surname>
		<name>Сергей</name>
		<fullname>Иванович</fullname>
		<birthdate>21.03.1982</birthdate>
		<dep>Снабжение</dep>
		<pos>Снабженец</pos>
		<type>Ставка</type>
		<pay>6800</pay>
	</Employee>
	<Employee>
		<surname>Сергеев</surname>
		<name>Михаил</name>
		<fullname>Игоревич</fullname>
		<birthdate>21.03.1983</birthdate>
		<dep>Снабжение</dep>
		<pos>Снабженец</pos>
		<type>Почасово</type>
		<pay>25</pay>
	</Employee>
	<Employee>
		<surname>Вальрьев</surname>
		<name>Евгений</name>
		<fullname>Николаевич</fullname>
		<birthdate>21.03.1984</birthdate>
		<dep>Сбыт</dep>
		<pos>Менеджер по сбыту</pos>
		<type>Почасово</type>
		<pay>30</pay>
	</Employee>
	<Employee>
		<surname>Пупков</surname>
		<name>Владимир</name>
		<fullname>Валерьевич</fullname>
		<birthdate>21.03.1985</birthdate>
		<dep>Сбыт</dep>
		<pos>Менеджер по сбыту</pos>
		<type>Почасово</type>
		<pay>32</pay>
	</Employee>
	<Employee>
		<surname>Сухов</surname>
		<name>Николай</name>
		<fullname>Андреевич</fullname>
		<birthdate>21.03.1986</birthdate>
		<dep>Бухгалтерия</dep>
		<pos>Бухгалтер</pos>
		<type>Ставка</type>
		<pay>7000</pay>
	</Employee>
	<Employee>
		<surname>Рыбов</surname>
		<name>Олег</name>
		<fullname>Сергеевич</fullname>
		<birthdate>21.03.1987</birthdate>
		<dep>Бухгалтерия</dep>
		<pos>Бухгалтер</pos>
		<type>Ставка</type>
		<pay>8000</pay>
	</Employee>
	<Employee>
		<surname>Бондаренко</surname>
		<name>Андрей</name>
		<fullname>Петрович</fullname>
		<birthdate>21.03.1988</birthdate>
		<dep>Бухгалтерия</dep>
		<pos>Бухгалтер</pos>
		<type>Почасово</type>
		<pay>28</pay>
	</Employee>
	<Employee>
		<surname>Клименко</surname>
		<name>Валерий</name>
		<fullname>Иванович</fullname>
		<birthdate>21.03.1989</birthdate>
		<dep>Бухгалтерия</dep>
		<pos>Гл. Бухгалтер</pos>
		<type>Почасово</type>
		<pay>35</pay>
	</Employee>
	<Employee>
		<surname>Сущенко</surname>
		<name>Виталий</name>
		<fullname>Игоревич</fullname>
		<birthdate>21.03.1990</birthdate>
		<dep>Сбыт</dep>
		<pos>Менеджер по сбыту</pos>
		<type>Ставка</type>
		<pay>8500</pay>
	</Employee>
	<Employee>
		<surname>Криворучко</surname>
		<name>Артем</name>
		<fullname>Николаевич</fullname>
		<birthdate>21.03.1991</birthdate>
		<dep>Сбыт</dep>
		<pos>Менеджер по сбыту</pos>
		<type>Ставка</type>
		<pay>7500</pay>
	</Employee>
	<Employee>
		<surname>Сухомлин</surname>
		<name>Игорь</name>
		<fullname>Валерьевич</fullname>
		<birthdate>21.03.1992</birthdate>
		<dep>Сбыт</dep>
		<pos>Менеджер по сбыту</pos>
		<type>Ставка</type>
		<pay>6800</pay>
	</Employee>
	<Employee>
		<surname>Петров</surname>
		<name>Иван</name>
		<fullname>Андреевич</fullname>
		<birthdate>21.03.1993</birthdate>
		<dep>Маркетинг</dep>
		<pos>Менеджер по рекламе</pos>
		<type>Почасово</type>
		<pay>36</pay>
	</Employee>
	<Employee>
		<surname>Сидоров</surname>
		<name>Петр</name>
		<fullname>Сергеевич</fullname>
		<birthdate>21.03.1994</birthdate>
		<dep>Маркетинг</dep>
		<pos>Менеджер по рекламе</pos>
		<type>Ставка</type>
		<pay>8000</pay>
	</Employee>
	<Employee>
		<surname>Иванов</surname>
		<name>Сергей</name>
		<fullname>Петрович</fullname>
		<birthdate>21.03.1995</birthdate>
		<dep>Маркетинг</dep>
		<pos>Менеджер по рекламе</pos>
		<type>Почасово</type>
		<pay>40</pay>
	</Employee>
	<Employee>
		<surname>Сергеев</surname>
		<name>Михаил</name>
		<fullname>Иванович</fullname>
		<birthdate>21.03.1996</birthdate>
		<dep>Маркетинг</dep>
		<pos>Менеджер по рекламе</pos>
		<type>Почасово</type>
		<pay>39</pay>
	</Employee>
	<Employee>
		<surname>Вальрьев</surname>
		<name>Евгений</name>
		<fullname>Игоревич</fullname>
		<birthdate>21.03.1997</birthdate>
		<dep>Доставка</dep>
		<pos>Водитель</pos>
		<type>Ставка</type>
		<pay>8500</pay>
	</Employee>
	<Employee>
		<surname>Пупков</surname>
		<name>Владимир</name>
		<fullname>Николаевич</fullname>
		<birthdate>21.03.1998</birthdate>
		<dep>Доставка</dep>
		<pos>Водитель</pos>
		<type>Почасово</type>
		<pay>42</pay>
	</Employee>
	<Employee>
		<surname>Сухов</surname>
		<name>Николай</name>
		<fullname>Валерьевич</fullname>
		<birthdate>21.03.1999</birthdate>
		<dep>Доставка</dep>
		<pos>Водитель</pos>
		<type>Ставка</type>
		<pay>9000</pay>
	</Employee>
	<Employee>
		<surname>Рыбов</surname>
		<name>Олег</name>
		<fullname>Андреевич</fullname>
		<birthdate>21.03.2000</birthdate>
		<dep>Доставка</dep>
		<pos>Экспедитор</pos>
		<type>Почасово</type>
		<pay>28</pay>
	</Employee>
	<Employee>
		<surname>Бондаренко</surname>
		<name>Андрей</name>
		<fullname>Валерьевич</fullname>
		<birthdate>21.03.2001</birthdate>
		<dep>Доставка</dep>
		<pos>Экспедитор</pos>
		<type>Почасово</type>
		<pay>28</pay>
	</Employee>
	<Employee>
		<surname>Клименко</surname>
		<name>Валерий</name>
		<fullname>Андреевич</fullname>
		<birthdate>21.03.2002</birthdate>
		<dep>Доставка</dep>
		<pos>Экспедитор</pos>
		<type>Почасово</type>
		<pay>28</pay>
	</Employee>
</List>